AreaVolume/ComputeCylinderVolume.py
AreaVolume/ComputeRectangleArea.py
AreaVolume/__init__.py
AreaVolume/SimpleMath/ComputeCircleAera.py
AreaVolume/SimpleMath/ComputeCircleArea.py
AreaVolume/SimpleMath/ComputeSphereVolume.py
AreaVolume/SimpleMath/__init__.py
AreaVolume-1.0.4.dist-info/METADATA
AreaVolume-1.0.4.dist-info/WHEEL
AreaVolume-1.0.4.dist-info/top_level.txt
AreaVolume-1.0.4.dist-info/RECORD
